georgstage/__init__.py
georgstage/__main__.py
georgstage/cli.py
georgstage/controller.py
georgstage/model.py
georgstage/view.py
georgstage/autofill/__init__.py
georgstage/autofill/lp.py
georgstage-0.2.19.dist-info/LICENCE.txt
georgstage-0.2.19.dist-info/METADATA
georgstage-0.2.19.dist-info/WHEEL
georgstage-0.2.19.dist-info/top_level.txt
georgstage-0.2.19.dist-info/RECORD
