Metadata-Version: 2.1
Name: georgstage
Version: 0.2.19
Summary: Library for Georg Stage
Author-email: Pimin Konstantin Kefaloukos <skipperkongen@gmail.com>
Requires-Python: >=3.7
License-File: LICENCE.txt
Requires-Dist: numpy
Requires-Dist: pandas
Requires-Dist: pulp
Provides-Extra: tests
Requires-Dist: build ; extra == 'tests'
Requires-Dist: twine ; extra == 'tests'
Requires-Dist: pytest ; extra == 'tests'
Requires-Dist: flake8 ; extra == 'tests'
